gnmi/proto/__init__.py
gnmi/proto/_internal/.gitkeep
gnmi/proto/_internal/__init__.py
gnmi/proto/_internal/gnmi/__init__.py
gnmi/proto/_internal/gnmi_ext/__init__.py
gnmi/proto/_internal/target/__init__.py
gnmi/proto/_legacy/.gitkeep
gnmi/proto/_legacy/collector/collector.proto
gnmi/proto/_legacy/collector/collector_pb2.py
gnmi/proto/_legacy/collector/collector_pb2_grpc.py
gnmi/proto/_legacy/gnmi/gnmi.proto
gnmi/proto/_legacy/gnmi/gnmi_pb2.py
gnmi/proto/_legacy/gnmi/gnmi_pb2_grpc.py
gnmi/proto/_legacy/gnmi_ext/gnmi_ext.proto
gnmi/proto/_legacy/gnmi_ext/gnmi_ext_pb2.py
gnmi/proto/_legacy/gnmi_ext/gnmi_ext_pb2_grpc.py
gnmi/proto/_legacy/target/target.proto
gnmi/proto/_legacy/target/target_pb2.py
gnmi/proto/_legacy/target/target_pb2_grpc.py
gnmi/proto/legacy.py
gnmi/proto/py.typed
gnmi_proto-0.1.0a4.dist-info/LICENSE
gnmi_proto-0.1.0a4.dist-info/WHEEL
gnmi_proto-0.1.0a4.dist-info/METADATA
gnmi_proto-0.1.0a4.dist-info/RECORD
