Metadata-Version: 2.1
Name: gnmi-proto
Version: 0.1.0a4
Summary: A python package containing gnmi proto specification and generated python code.
Home-page: https://github.com/python-gnxi
License: APLv2
Author: Arun Babu Neelicattu
Author-email: arun.neelicattu@gmail.com
Requires-Python: >=3.6,<4.0
Classifier: Development Status :: 2 - Pre-Alpha
Classifier: License :: Other/Proprietary License
Classifier: Programming Language :: Python :: 3
Classifier: Programming Language :: Python :: 3.6
Classifier: Programming Language :: Python :: 3.7
Classifier: Programming Language :: Python :: 3.8
Classifier: Programming Language :: Python :: 3.9
Classifier: Topic :: Software Development
Classifier: Topic :: Software Development :: Libraries
Classifier: Topic :: System :: Networking
Classifier: Typing :: Typed
Requires-Dist: betterproto (>=2.0.0b1,<3.0.0)
Requires-Dist: grpcio (>=1.30,<2.0)
Requires-Dist: protobuf (>=3.12,<4.0)
Project-URL: Repository, https://github.com/python-gnxi/python-gnmi-proto
